src/cli.py
jay_lint-0.0.3.dist-info/LICENSE
jay_lint-0.0.3.dist-info/METADATA
jay_lint-0.0.3.dist-info/WHEEL
jay_lint-0.0.3.dist-info/entry_points.txt
jay_lint-0.0.3.dist-info/RECORD
